apika/__init__.py
apika/core.py
apika-0.1.2.dist-info/METADATA
apika-0.1.2.dist-info/WHEEL
apika-0.1.2.dist-info/top_level.txt
apika-0.1.2.dist-info/RECORD
